ai_ped_red_team/__init__.py
ai_ped_red_team/__main__.py
ai_ped_red_team/cli.py
ai_ped_red_team/config.py
ai_ped_red_team/agents/__init__.py
ai_ped_red_team/agents/analyst.py
ai_ped_red_team/agents/generator.py
ai_ped_red_team/agents/tester.py
ai_ped_red_team/analyze/__init__.py
ai_ped_red_team/analyze/metrics.py
ai_ped_red_team/analyze/report.py
ai_ped_red_team/analyze/stats.py
ai_ped_red_team/axes/__init__.py
ai_ped_red_team/axes/config.py
ai_ped_red_team/generate/__init__.py
ai_ped_red_team/generate/variants.py
ai_ped_red_team/models/__init__.py
ai_ped_red_team/models/gateway.py
ai_ped_red_team/models/schema.py
ai_ped_red_team/models/statecheck.py
ai_ped_red_team/normalize/__init__.py
ai_ped_red_team/normalize/textnorm.py
ai_ped_red_team/run/__init__.py
ai_ped_red_team/run/runner.py
ai_ped_red_team/templates/__init__.py
ai_ped_red_team/templates/loader.py
ai_ped_red_team/templates/examples/ehcp_pair/ehcp_anthony.txt
ai_ped_red_team/templates/examples/ehcp_pair/ehcp_sarah.txt
ai_ped_red_team/templates/examples/questionnaire/q_ehcp_gender.json
ai_ped_red_team-0.1.0.dist-info/METADATA
ai_ped_red_team-0.1.0.dist-info/WHEEL
ai_ped_red_team-0.1.0.dist-info/entry_points.txt
ai_ped_red_team-0.1.0.dist-info/licenses/LICENSE
ai_ped_red_team-0.1.0.dist-info/RECORD
