Metadata-Version: 2.4
Name: ai-ped-red-team
Version: 0.1.0
Summary: Template-driven pedagogy red-team toolkit for LLM bias studies (EHCP demo).
Author-email: SoftOboros <dev@softoboros.com>
License: MIT
License-File: LICENSE
Classifier: Intended Audience :: Education
Classifier: License :: OSI Approved :: MIT License
Classifier: Programming Language :: Python :: 3
Classifier: Programming Language :: Python :: 3 :: Only
Classifier: Programming Language :: Python :: 3.10
Classifier: Programming Language :: Python :: 3.11
Classifier: Programming Language :: Python :: 3.12
Classifier: Topic :: Scientific/Engineering :: Information Analysis
Requires-Python: >=3.10
Requires-Dist: detoxify>=0.5
Requires-Dist: httpx>=0.27
Requires-Dist: jinja2>=3.1
Requires-Dist: jsonschema>=4.22
Requires-Dist: litellm>=1.41
Requires-Dist: markdown>=3.4
Requires-Dist: networkx>=3.3
Requires-Dist: numpy<2,>=1.26
Requires-Dist: pandas>=2.2
Requires-Dist: pydantic-settings>=2
Requires-Dist: pydantic>=2.7
Requires-Dist: rich>=14.0
Requires-Dist: scikit-learn>=1.4
Requires-Dist: spacy>=3.7
Requires-Dist: statsmodels>=0.14
Requires-Dist: textstat>=0.7
Requires-Dist: tomli>=2; python_version < '3.11'
Requires-Dist: torch>=2.1
Requires-Dist: typer>=0.12
Requires-Dist: vadersentiment>=3.3
Provides-Extra: dev
Requires-Dist: black>=24.8; extra == 'dev'
Requires-Dist: hypothesis>=6; extra == 'dev'
Requires-Dist: pre-commit>=3.7; extra == 'dev'
Requires-Dist: pytest>=8; extra == 'dev'
Requires-Dist: ruff>=0.6; extra == 'dev'
Provides-Extra: docs
Requires-Dist: mkdocs-material>=9.5; extra == 'docs'
Requires-Dist: mkdocs>=1.6; extra == 'docs'
